i18n_toml/__init__.py
i18n_toml/lib.py
i18n_toml/py.typed
i18n_toml-0.2.dist-info/WHEEL
i18n_toml-0.2.dist-info/METADATA
i18n_toml-0.2.dist-info/RECORD
