Metadata-Version: 2.3
Name: i18n-toml
Version: 0.2
Summary: Internalization tool for Python projects using `.toml` files for storing text content
Keywords: n18i,internalization,localization,toml
Author: Maxim Huzmiev
Author-email: Maxim Huzmiev <max@huzm.ru>
Classifier: Programming Language :: Python :: 3.11
Classifier: Intended Audience :: Developers
Classifier: Operating System :: OS Independent
Classifier: Development Status :: 4 - Beta
Requires-Python: >=3.11
Project-URL: Changelog, https://github.com/maxhuzm/i18n-toml/blob/master/CHANGELOG.md
Project-URL: Documentation, https://github.com/maxhuzm/i18n-toml/blob/master/README.md
Project-URL: Homepage, https://github.com/maxhuzm/i18n-toml
Project-URL: Repository, https://github.com/maxhuzm/i18n-toml
